kerastroke/__init__.py
kerastroke/neuroplast.py
kerastroke/pruning.py
kerastroke/stroke.py
kerastroke-2.1.1.data/scripts/__init__.py
kerastroke-2.1.1.dist-info/LICENSE
kerastroke-2.1.1.dist-info/METADATA
kerastroke-2.1.1.dist-info/WHEEL
kerastroke-2.1.1.dist-info/top_level.txt
kerastroke-2.1.1.dist-info/RECORD
