Metadata-Version: 2.1
Name: kerastroke
Version: 2.1.1
Summary: A suite of the generalization-improvement techniques Stroke, Pruning, and NeuroPlast
Home-page: https://github.com/CharlesAverill/kerastroke/
Author: Charles Averill
Author-email: charlesaverill20@gmail.com
License: UNKNOWN
Platform: UNKNOWN
Classifier: Programming Language :: Python :: 3
Classifier: License :: OSI Approved :: MIT License
Classifier: Operating System :: OS Independent
Requires-Dist: tensorflow
Requires-Dist: numpy
